line_placement_plot/__init__.py
st_line_placement_plot_v1-0.0.1.dist-info/LICENSE
st_line_placement_plot_v1-0.0.1.dist-info/METADATA
st_line_placement_plot_v1-0.0.1.dist-info/WHEEL
st_line_placement_plot_v1-0.0.1.dist-info/top_level.txt
st_line_placement_plot_v1-0.0.1.dist-info/RECORD
