Metadata-Version: 2.1
Name: st-line-placement-plot-v1
Version: 0.0.1
Summary: A tool to place lines on an image and get back the coordinates for those lines
Home-page: 
Author: Elliot Glas
Author-email: elliot.glas@hotmail.se
Requires-Python: >=3.6
License-File: LICENSE
Requires-Dist: streamlit (>=0.63)
